tensorflow_extra/__init__.py
tensorflow_extra/activations.py
tensorflow_extra/layers.py
tensorflow_extra/utils.py
tensorflow_extra/version.py
tensorflow_extra-1.0.2.dist-info/LICENSE.md
tensorflow_extra-1.0.2.dist-info/METADATA
tensorflow_extra-1.0.2.dist-info/WHEEL
tensorflow_extra-1.0.2.dist-info/top_level.txt
tensorflow_extra-1.0.2.dist-info/RECORD
